ocs/__init__.py
ocs/__main__.py
ocs/args.py
ocs/data.py
ocs/db.py
ocs/languages.py
ocs/problem.py
ocs/request.py
ocs/server.py
ocs/user.py
opencontest_server-2.8.0.dist-info/LICENSE
opencontest_server-2.8.0.dist-info/METADATA
opencontest_server-2.8.0.dist-info/WHEEL
opencontest_server-2.8.0.dist-info/entry_points.txt
opencontest_server-2.8.0.dist-info/top_level.txt
opencontest_server-2.8.0.dist-info/RECORD
