Metadata-Version: 2.1
Name: opencontest-server
Version: 2.8.0
Summary: An OpenContest server written in Python
Home-page: https://github.com/LadueCS/OpenContest-Server
Author: Anthony Wang
Author-email: ta180m@pm.me
License: UNKNOWN
Project-URL: Bug Tracker, https://github.com/LadueCS/OpenContest-Server/issues
Platform: UNKNOWN
Classifier: Programming Language :: Python :: 3
Classifier: License :: OSI Approved :: GNU Affero General Public License v3
Classifier: Operating System :: OS Independent
Classifier: Environment :: Console
Classifier: Intended Audience :: System Administrators
License-File: LICENSE
Requires-Dist: requests
